<?xml version="1.0" encoding="UTF-8"?>
<MetaDataObject xmlns="http://v8.1c.ru/8.3/MDClasses" xmlns:app="http://v8.1c.ru/8.2/managed-application/core" xmlns:cfg="http://v8.1c.ru/8.1/data/enterprise/current-config" xmlns:cmi="http://v8.1c.ru/8.2/managed-application/cmi" xmlns:ent="http://v8.1c.ru/8.1/data/enterprise" xmlns:lf="http://v8.1c.ru/8.2/managed-application/logform" xmlns:style="http://v8.1c.ru/8.1/data/ui/style" xmlns:sys="http://v8.1c.ru/8.1/data/ui/fonts/system" xmlns:v8="http://v8.1c.ru/8.1/data/core" xmlns:v8ui="http://v8.1c.ru/8.1/data/ui" xmlns:web="http://v8.1c.ru/8.1/data/ui/colors/web" xmlns:win="http://v8.1c.ru/8.1/data/ui/colors/windows" xmlns:xen="http://v8.1c.ru/8.3/xcf/enums" xmlns:xpr="http://v8.1c.ru/8.3/xcf/predef" xmlns:xr="http://v8.1c.ru/8.3/xcf/readable" xmlns:xs="http://www.w3.org/2001/XMLSchema" xmlns:xsi="http://www.w3.org/2001/XMLSchema-instance" version="2.11">
	<WSReference uuid="6cd25d35-34a1-4192-a178-125afc7c3591">
		<InternalInfo>
			<xr:GeneratedType name="WSReferenceManager.ZSD_010_FG_1C" category="Manager">
				<xr:TypeId>fea3f549-af6f-41a2-b7a1-345fb909eeec</xr:TypeId>
				<xr:ValueId>7f5c29ae-2ef3-4f0f-ba6f-9b0ef5fcae4a</xr:ValueId>
			</xr:GeneratedType>
		</InternalInfo>
		<Properties>
			<Name>ZSD_010_FG_1C</Name>
			<Synonym>
				<v8:item>
					<v8:lang>ru</v8:lang>
					<v8:content>ZSD 010 f g 1 C</v8:content>
				</v8:item>
			</Synonym>
			<Comment/>
			<LocationURL>file://D:/s1/apt/2.xml</LocationURL>
		</Properties>
	</WSReference>
</MetaDataObject>